opensearch_rest_resources/__init__.py
opensearch_rest_resources/py.typed
opensearch_rest_resources/_jsii/__init__.py
opensearch_rest_resources/_jsii/opensearch-rest-resources@0.0.13.jsii.tgz
opensearch_rest_resources-0.0.13.dist-info/LICENSE
opensearch_rest_resources-0.0.13.dist-info/METADATA
opensearch_rest_resources-0.0.13.dist-info/WHEEL
opensearch_rest_resources-0.0.13.dist-info/top_level.txt
opensearch_rest_resources-0.0.13.dist-info/RECORD
